harvesterpy/__init__.py
harvesterpy/client.py
harvesterpy/exceptions.py
harvesterpy/resources/__init__.py
harvesterpy/resources/base.py
harvesterpy/resources/images.py
harvesterpy/resources/networks.py
harvesterpy/resources/nodes.py
harvesterpy/resources/settings.py
harvesterpy/resources/virtual_machines.py
harvesterpy/resources/volumes.py
harvesterpy-0.1.5.dist-info/licenses/LICENSE
harvesterpy-0.1.5.dist-info/METADATA
harvesterpy-0.1.5.dist-info/WHEEL
harvesterpy-0.1.5.dist-info/top_level.txt
harvesterpy-0.1.5.dist-info/RECORD
