Metadata-Version: 2.4
Name: harvesterpy
Version: 0.1.5
Summary: A Python library to interface with SUSE Harvester HCI
Home-page: https://github.com/bpmconsultag/HarvesterPy
Author: bpmconsultag
License: MIT
Project-URL: Homepage, https://github.com/bpmconsultag/HarvesterPy
Project-URL: Repository, https://github.com/bpmconsultag/HarvesterPy
Requires-Python: >=3.8
License-File: LICENSE
Requires-Dist: requests>=2.25.0
Dynamic: home-page
Dynamic: license-file
Dynamic: requires-python
